pyd/__init__.py
pyd/hello.py
pyd/hello2.py
chenwenjun-0.0.1.dist-info/METADATA
chenwenjun-0.0.1.dist-info/WHEEL
chenwenjun-0.0.1.dist-info/top_level.txt
chenwenjun-0.0.1.dist-info/RECORD
